AUTHORS.rst
CHANGES.rst
LICENSE.rst
MANIFEST.in
README.rst
setup.py
monoseq/__init__.py
monoseq/commands.py
monoseq/ipynb.py
monoseq/monoseq.py
monoseq.egg-info/PKG-INFO
monoseq.egg-info/SOURCES.txt
monoseq.egg-info/dependency_links.txt
monoseq.egg-info/entry_points.txt
monoseq.egg-info/top_level.txt