Metadata-Version: 1.1
Name: monoseq
Version: 1.2.0
Summary: A Python library for pretty-printing DNA and protein sequences using a monospace font
Home-page: https://github.com/martijnvermaat/monoseq
Author: Martijn Vermaat
Author-email: martijn@vermaat.name
License: MIT License
Keywords: bioinformatics
Platform: any
Classifier: Development Status :: 3 - Alpha
Classifier: Intended Audience :: Developers
Classifier: Intended Audience :: Science/Research
Classifier: Operating System :: OS Independent
Classifier: Programming Language :: Python
Classifier: Topic :: Scientific/Engineering
